{
    "player_id": "1194795",
    "player_name": "M Pathirana",
    "overall_performance": {
        "GT": {
            "total_runs_scored": 0,
            "total_wickets_taken": 2,
            "highest_score": 0,
            "best_bowling_figure": "2/18",
            "batting_average": 0.0,
            "teams_winning_batting_first": 0,
            "teams_winning_batting_second": 1,
            "batting_strike_rate": 0.0,
            "bowling_strike_rate": 12.0
        },
        "PBKS": {
            "total_runs_scored": 0,
            "total_wickets_taken": 1,
            "highest_score": 0,
            "best_bowling_figure": "1/42",
            "batting_average": 0.0,
            "teams_winning_batting_first": 0,
            "teams_winning_batting_second": 0,
            "batting_strike_rate": 0.0,
            "bowling_strike_rate": 24.0
        },
        "LSG": {
            "total_runs_scored": 0,
            "total_wickets_taken": 2,
            "highest_score": 0,
            "best_bowling_figure": "2/35",
            "batting_average": 0.0,
            "teams_winning_batting_first": 1,
            "teams_winning_batting_second": 1,
            "batting_strike_rate": 0.0,
            "bowling_strike_rate": 18.0
        },
        "DC": {
            "total_runs_scored": 0,
            "total_wickets_taken": 3,
            "highest_score": 0,
            "best_bowling_figure": "3/37",
            "batting_average": 0.0,
            "teams_winning_batting_first": 0,
            "teams_winning_batting_second": 1,
            "batting_strike_rate": 0.0,
            "bowling_strike_rate": 10.0
        },
        "MI": {
            "total_runs_scored": 0,
            "total_wickets_taken": 1,
            "highest_score": 0,
            "best_bowling_figure": "1/27",
            "batting_average": 0.0,
            "teams_winning_batting_first": 0,
            "teams_winning_batting_second": 0,
            "batting_strike_rate": 0.0,
            "bowling_strike_rate": 24.0
        },
        "RR": {
            "total_runs_scored": 0,
            "total_wickets_taken": 2,
            "highest_score": 0,
            "best_bowling_figure": "2/27",
            "batting_average": 0.0,
            "teams_winning_batting_first": 0,
            "teams_winning_batting_second": 0,
            "batting_strike_rate": 0.0,
            "bowling_strike_rate": 12.0
        },
        "SRH": {
            "total_runs_scored": 0,
            "total_wickets_taken": 1,
            "highest_score": 0,
            "best_bowling_figure": "1/29",
            "batting_average": 0.0,
            "teams_winning_batting_first": 0,
            "teams_winning_batting_second": 0,
            "batting_strike_rate": 0.0,
            "bowling_strike_rate": 24.0
        },
        "KKR": {
            "total_runs_scored": 0,
            "total_wickets_taken": 0,
            "highest_score": 0,
            "best_bowling_figure": "-",
            "batting_average": 0.0,
            "teams_winning_batting_first": 0,
            "teams_winning_batting_second": 0,
            "batting_strike_rate": 0.0,
            "bowling_strike_rate": 0.0
        },
        "RCB": {
            "total_runs_scored": 0,
            "total_wickets_taken": 1,
            "highest_score": 0,
            "best_bowling_figure": "1/45",
            "batting_average": 0.0,
            "teams_winning_batting_first": 0,
            "teams_winning_batting_second": 1,
            "batting_strike_rate": 0.0,
            "bowling_strike_rate": 24.0
        }
    }
}