{
    "player_id": "917231",
    "player_name": "BR Sharath",
    "overall_performance": {
        "PBKS": {
            "total_runs": 35,
            "total_wickets": 0,
            "highest_score": 35,
            "best_bowling_figure": "0/0",
            "batting_average": 35.0,
            "teams_winning_batting_first": 0,
            "teams_winning_batting_second": 0,
            "batting_strike_rate": 120.69,
            "bowling_strike_rate": null
        },
        "LSG": {
            "total_runs": 18,
            "total_wickets": 0,
            "highest_score": 18,
            "best_bowling_figure": "0/0",
            "batting_average": 18.0,
            "teams_winning_batting_first": 0,
            "teams_winning_batting_second": 0,
            "batting_strike_rate": 100.0,
            "bowling_strike_rate": null
        },
        "DC": {
            "total_runs": 22,
            "total_wickets": 0,
            "highest_score": 22,
            "best_bowling_figure": "0/0",
            "batting_average": 22.0,
            "teams_winning_batting_first": 0,
            "teams_winning_batting_second": 0,
            "batting_strike_rate": 95.65,
            "bowling_strike_rate": null
        },
        "CSK": {
            "total_runs": 0,
            "total_wickets": 0,
            "highest_score": 0,
            "best_bowling_figure": "0/0",
            "batting_average": 0.0,
            "teams_winning_batting_first": 0,
            "teams_winning_batting_second": 0,
            "batting_strike_rate": 0.0,
            "bowling_strike_rate": null
        },
        "MI": {
            "total_runs": 0,
            "total_wickets": 0,
            "highest_score": 0,
            "best_bowling_figure": "0/0",
            "batting_average": 0.0,
            "teams_winning_batting_first": 0,
            "teams_winning_batting_second": 0,
            "batting_strike_rate": 0.0,
            "bowling_strike_rate": null
        },
        "RR": {
            "total_runs": 0,
            "total_wickets": 0,
            "highest_score": 0,
            "best_bowling_figure": "0/0",
            "batting_average": 0.0,
            "teams_winning_batting_first": 0,
            "teams_winning_batting_second": 0,
            "batting_strike_rate": 0.0,
            "bowling_strike_rate": null
        },
        "SRH": {
            "total_runs": 0,
            "total_wickets": 0,
            "highest_score": 0,
            "best_bowling_figure": "0/0",
            "batting_average": 0.0,
            "teams_winning_batting_first": 0,
            "teams_winning_batting_second": 0,
            "batting_strike_rate": 0.0,
            "bowling_strike_rate": null
        },
        "KKR": {
            "total_runs": 0,
            "total_wickets": 0,
            "highest_score": 0,
            "best_bowling_figure": "0/0",
            "batting_average": 0.0,
            "teams_winning_batting_first": 0,
            "teams_winning_batting_second": 0,
            "batting_strike_rate": 0.0,
            "bowling_strike_rate": null
        },
        "RCB": {
            "total_runs": 0,
            "total_wickets": 0,
            "highest_score": 0,
            "best_bowling_figure": "0/0",
            "batting_average": 0.0,
            "teams_winning_batting_first": 0,
            "teams_winning_batting_second": 0,
            "batting_strike_rate": 0.0,
            "bowling_strike_rate": null
        }
    }
}